dss_sdk/__init__.py
dss_sdk/__version__.py
dss_sdk/cli.py
dss_sdk/credentials.py
dss_sdk/models.py
dss_sdk/server.py
dss_sdk/utilities.py
dss_sdk-1.3.0.dist-info/LICENSE
dss_sdk-1.3.0.dist-info/METADATA
dss_sdk-1.3.0.dist-info/WHEEL
dss_sdk-1.3.0.dist-info/entry_points.txt
dss_sdk-1.3.0.dist-info/top_level.txt
dss_sdk-1.3.0.dist-info/RECORD
