Metadata-Version: 2.1
Name: dss-sdk
Version: 1.3.0
Summary: A better SDK for Delinea Secret Server
Author: riebecj
License: GNU GENERAL PUBLIC LICENSE
Project-URL: home-page, https://github.com/riebecj/dss-sdk
Keywords: delinea,secret,server,cli,dss,dss-sdk
Classifier: Operating System :: OS Independent
Classifier: Programming Language :: Python :: 3.8
Classifier: Programming Language :: Python :: 3.9
Classifier: Programming Language :: Python :: 3.10
Classifier: Programming Language :: Python :: 3.11
Classifier: Development Status :: 3 - Alpha
Classifier: Environment :: Console
Classifier: Framework :: Pydantic :: 2
Classifier: Intended Audience :: Developers
Classifier: Intended Audience :: End Users/Desktop
Classifier: Intended Audience :: Information Technology
Classifier: License :: OSI Approved :: GNU General Public License v3 or later (GPLv3+)
Classifier: Programming Language :: Python :: 3 :: Only
Classifier: Topic :: Security
Classifier: Topic :: Software Development
Classifier: Topic :: Software Development :: Libraries :: Python Modules
Classifier: Topic :: Utilities
Requires-Python: >=3.8
License-File: LICENSE
Requires-Dist: httpx ~=0.26
Requires-Dist: pydantic ~=2.4
Requires-Dist: typer ~=0.9
Requires-Dist: click ~=8.1
Requires-Dist: rich ~=13.7
Requires-Dist: pyperclip ~=1.8
Requires-Dist: toml ~=0.10
Provides-Extra: dev
Requires-Dist: pytest ~=7.4 ; extra == 'dev'
Requires-Dist: pytest-cov ~=4.1 ; extra == 'dev'
Requires-Dist: ruff ~=0.3 ; extra == 'dev'
